cyberfusion/RPCClient/__init__.py
cyberfusion/RPCClient/_rpc.py
cyberfusion/RPCClient/_utilities.py
cyberfusion/RPCClient/containers.py
cyberfusion/RPCClient/enums.py
python3_cyberfusion_rpc_client-1.1.dist-info/METADATA
python3_cyberfusion_rpc_client-1.1.dist-info/WHEEL
python3_cyberfusion_rpc_client-1.1.dist-info/top_level.txt
python3_cyberfusion_rpc_client-1.1.dist-info/RECORD
