Metadata-Version: 2.4
Name: python3-cyberfusion-rpc-client
Version: 1.1
Summary: Developer-friendly RPC client to publish RPC requests and receive responses.
Author-email: Cyberfusion <support@cyberfusion.io>
Project-URL: Source, https://github.com/CyberfusionIO/python3-cyberfusion-rpc-client
Requires-Dist: pika==1.3.2
